{"cameraMode":{"drawMode":0,"name":"Shaded","section":"Shading Mode"},"sceneLighting":true,"audioPlay":false,"sceneViewState":{"m_AlwaysRefresh":false,"showFog":true,"showSkybox":true,"showFlares":true,"showImageEffects":true,"showParticleSystems":true,"showVisualEffectGraphs":true,"m_FxEnabled":true},"in2DMode":false,"pivot":{"x":9.57468318939209,"y":2.5580577850341799,"z":-26.94815444946289},"rotation":{"x":0.26515859365463259,"y":-0.36160990595817568,"z":0.10806568711996079,"w":0.8872730135917664},"size":11.631257057189942,"orthographic":false}